medimgkit/__init__.py
medimgkit/dicom_utils.py
medimgkit/format_detection.py
medimgkit/io_utils.py
medimgkit/modality_detector.py
medimgkit/nifti_utils.py
medimgkit/readers.py
medimgkit-0.11.3.dist-info/METADATA
medimgkit-0.11.3.dist-info/WHEEL
medimgkit-0.11.3.dist-info/top_level.txt
medimgkit-0.11.3.dist-info/RECORD
