Metadata-Version: 2.4
Name: medimgkit
Version: 0.11.3
Summary: A comprehensive toolkit for medical image processing, including DICOM, NIfTI, and multi-format I/O utilities
License-Expression: MIT
Project-URL: Homepage, https://github.com/SonanceAI/medimgkit
Project-URL: Repository, https://github.com/SonanceAI/medimgkit
Project-URL: Bug Tracker, https://github.com/SonanceAI/medimgkit/issues
Keywords: medical,imaging,dicom,nifti,healthcare,radiology,medical-imaging,image-processing
Classifier: Development Status :: 3 - Alpha
Classifier: Intended Audience :: Healthcare Industry
Classifier: Intended Audience :: Science/Research
Classifier: Operating System :: OS Independent
Classifier: Programming Language :: Python :: 3
Classifier: Programming Language :: Python :: 3.9
Classifier: Programming Language :: Python :: 3.10
Classifier: Programming Language :: Python :: 3.11
Classifier: Programming Language :: Python :: 3.12
Classifier: Topic :: Scientific/Engineering :: Medical Science Apps.
Classifier: Topic :: Software Development :: Libraries :: Python Modules
Requires-Python: >=3.9
Requires-Dist: pydicom>=2.3.0
Requires-Dist: nibabel>=3.2.0
Requires-Dist: numpy>=1.20.0
Requires-Dist: Pillow>=8.0.0
Requires-Dist: opencv-python>=4.5.0
Requires-Dist: tqdm>=4.60.0
Requires-Dist: python-magic>=0.4.24
Requires-Dist: puremagic>=1.30
Requires-Dist: plotly>=5.19.0
Requires-Dist: nbformat>=4.3.0
Requires-Dist: pandas>=1.5.3
Requires-Dist: pylibjpeg>=2.0.0
Requires-Dist: pylibjpeg-libjpeg>=2.0.0
Requires-Dist: deprecated>=1.2.0
Provides-Extra: dev
Requires-Dist: pytest>=6.0; extra == "dev"
Requires-Dist: pytest-cov; extra == "dev"
Requires-Dist: flake8; extra == "dev"
Provides-Extra: test
Requires-Dist: pytest>=6.0; extra == "test"
Requires-Dist: pytest-cov; extra == "test"
Provides-Extra: docs
Requires-Dist: sphinx; extra == "docs"
Requires-Dist: sphinx-rtd-theme; extra == "docs"
